README.rst
setup.py
netcfg/__init__.py
netcfg/client.py
netcfg/configuration.py
netcfg/container.py
netcfg/daemon.py
netcfg.egg-info/PKG-INFO
netcfg.egg-info/SOURCES.txt
netcfg.egg-info/dependency_links.txt
netcfg.egg-info/not-zip-safe
netcfg.egg-info/requires.txt
netcfg.egg-info/top_level.txt
netcfg/network/__init__.py
netcfg/network/base.py
netcfg/network/bridge.py
scripts/netcfg