Metadata-Version: 1.1
Name: netcfg
Version: 0.1.0
Summary: Network configuration of Docker containers.
Home-page: https://github.com/wlanslovenija/netcfg
Author: wlan slovenija
Author-email: open@wlan-si.net
License: AGPLv3
Platform: UNKNOWN
Classifier: Development Status :: 4 - Beta
Classifier: Intended Audience :: System Administrators
Classifier: License :: OSI Approved :: GNU Affero General Public License v3
Classifier: Operating System :: POSIX :: Linux
Classifier: Programming Language :: Python
